Metadata-Version: 2.1
Name: sintx
Version: 0.1.4
Summary: Sintacs Modules
Home-page: https://facebook.com/sintxcs
Author: Sintacs.
Author-email: sintacs@isnotdev.com
License: MIT
Keywords: Sintxcs,Sintacs,Sintx
Platform: UNKNOWN
Classifier: Development Status :: 5 - Production/Stable
Classifier: Intended Audience :: Education
Classifier: Operating System :: Microsoft :: Windows :: Windows 10
Classifier: License :: OSI Approved :: MIT License
Classifier: Programming Language :: Python :: 3
License-File: LICENCE.txt
